topsis/__init__.py
topsis/topsis.py
102217109_topsis-1.0.1.dist-info/METADATA
102217109_topsis-1.0.1.dist-info/WHEEL
102217109_topsis-1.0.1.dist-info/top_level.txt
102217109_topsis-1.0.1.dist-info/RECORD
