Metadata-Version: 2.1
Name: 102217109_topsis
Version: 1.0.1
Summary: A simple TOPSIS implementation package.
Author: Prisha Singh
Author-email: prishasingh1104@gmail.com
Classifier: Programming Language :: Python :: 3
Classifier: License :: OSI Approved :: MIT License
Classifier: Operating System :: OS Independent
Requires-Python: >=3.6
Requires-Dist: numpy
